yud92022/__init__.py
yud92022/goodbye.py
yud92022-0.1.2.dist-info/LICENSE
yud92022-0.1.2.dist-info/METADATA
yud92022-0.1.2.dist-info/WHEEL
yud92022-0.1.2.dist-info/top_level.txt
yud92022-0.1.2.dist-info/RECORD
