Metadata-Version: 2.1
Name: yud92022
Version: 0.1.2
Summary: A small creactive goodbye project for my students.
Home-page: https://github.com/tomereliel0/yud_9_2022
Author: Tomer Eliel
Author-email: tomereliel.dev@gmail.com
Project-URL: Bug Tracker, https://github.com/tomereliel0/yud_9_2022/issues
Classifier: Programming Language :: Python :: 3
Classifier: License :: OSI Approved :: MIT License
Classifier: Operating System :: OS Independent
Requires-Python: >=3.6
License-File: LICENSE
Requires-Dist: keyboard
